namara/__init__.py
namara-0.2.0.dist-info/LICENSE.md
namara-0.2.0.dist-info/METADATA
namara-0.2.0.dist-info/WHEEL
namara-0.2.0.dist-info/top_level.txt
namara-0.2.0.dist-info/RECORD
