Metadata-Version: 2.1
Name: namara
Version: 0.2.0
Summary: The official Python client for the Namara data collaboration platform
Home-page: https://github.com/namara-io/namara-python
Author: ThinkData Works
Author-email: info@namara.io
License: Apache-2.0
Keywords: namara,open data,api,canada,us,government,independent
Platform: UNKNOWN
Requires-Dist: requests-futures (==0.9.9)
